MANIFEST.in
README.txt
setup.py
sffj-clock.ini
xplclock.py
expel.apps.clock.egg-info/PKG-INFO
expel.apps.clock.egg-info/SOURCES.txt
expel.apps.clock.egg-info/dependency_links.txt
expel.apps.clock.egg-info/requires.txt
expel.apps.clock.egg-info/top_level.txt