Metadata-Version: 1.0
Name: expel.apps.clock
Version: 0.1
Summary: xPL Clock - Sends out datetime.basic information every `tick` minutes.
Home-page: http://www.sffjunkie.co.uk/python-expel.html#clock
Author: Simon Kennedy
Author-email: code@sffjunkie.co.uk
License: Apache-2.0
Platform: UNKNOWN
